{"GNU Lesser General Public License v2.1": 18, "GNU Affero General Public License v3.0": 33, "The Unlicense": 68, "MIT License": 1748, "GNU General Public License v2.0": 241, "GNU General Public License v3.0": 300, "Apache License 2.0": 460, "Mozilla Public License 2.0": 23, "BSD 3-clause \"New\" or \"Revised\" License": 166, "Eclipse Public License 1.0": 14, "none": 7426, "GNU Lesser General Public License v3.0": 41, "Other": 384, "Creative Commons Attribution 4.0": 0, "BSD 2-clause \"Simplified\" License": 64}